py2shpss/HPSS.py
py2shpss/__init__.py
py2shpss/metric.py
py2shpss/py2shpss.py
py2shpss/samprate.py
py2shpss-0.1.0a4.dist-info/LICENSE
py2shpss-0.1.0a4.dist-info/METADATA
py2shpss-0.1.0a4.dist-info/WHEEL
py2shpss-0.1.0a4.dist-info/top_level.txt
py2shpss-0.1.0a4.dist-info/RECORD
