Metadata-Version: 2.1
Name: py2shpss
Version: 0.1.0a4
Summary: A Python implementation of two-stage HPSS (a singing voice extraction method)
Home-page: https://github.com/tachi-hi/py2shpss
Author: Hideyuki Tachibana
Author-email: tachi-hi@users.noreply.github.com
License: MIT
Keywords: py2shpss
Classifier: Development Status :: 3 - Alpha
Classifier: Intended Audience :: Science/Research
Classifier: License :: OSI Approved :: MIT License
Classifier: Topic :: Multimedia :: Sound/Audio
Classifier: Programming Language :: Python :: 3
Classifier: Programming Language :: Python :: 3.7
Classifier: Programming Language :: Python :: 3.8
Classifier: Programming Language :: Python :: 3.9
Requires-Python: >=3.6
License-File: LICENSE
Requires-Dist: scipy (>=1.5.2)
Requires-Dist: numpy (>=1.19.2)
Requires-Dist: matplotlib (>=3.3.1)
Requires-Dist: nptyping (>=1.3.0)
